dflask/__init__.py
dflask-1.0.2.dist-info/LICENSE
dflask-1.0.2.dist-info/METADATA
dflask-1.0.2.dist-info/WHEEL
dflask-1.0.2.dist-info/top_level.txt
dflask-1.0.2.dist-info/RECORD
