Metadata-Version: 2.1
Name: dflask
Version: 1.0.2
Summary: Use responses for Flask directly
Home-page: https://github.com/donno2048/Direct-Flask
Author: Elisha Hollander
Author-email: just4now666666@gmail.com
License: MIT
Project-URL: Documentation, https://github.com/donno2048/Direct-Flask#readme
Project-URL: Bug Reports, https://github.com/donno2048/Direct-Flask/issues
Project-URL: Source Code, https://github.com/donno2048/Direct-Flask
Platform: UNKNOWN
Classifier: Programming Language :: Python :: 3
Requires-Python: >=3.0
License-File: LICENSE
Requires-Dist: Flask (>=2.0.1)
